azure/mgmt/recoveryservicesdatareplication/__init__.py
azure/mgmt/recoveryservicesdatareplication/_client.py
azure/mgmt/recoveryservicesdatareplication/_configuration.py
azure/mgmt/recoveryservicesdatareplication/_patch.py
azure/mgmt/recoveryservicesdatareplication/_version.py
azure/mgmt/recoveryservicesdatareplication/py.typed
azure/mgmt/recoveryservicesdatareplication/_utils/__init__.py
azure/mgmt/recoveryservicesdatareplication/_utils/model_base.py
azure/mgmt/recoveryservicesdatareplication/_utils/serialization.py
azure/mgmt/recoveryservicesdatareplication/aio/__init__.py
azure/mgmt/recoveryservicesdatareplication/aio/_client.py
azure/mgmt/recoveryservicesdatareplication/aio/_configuration.py
azure/mgmt/recoveryservicesdatareplication/aio/_patch.py
azure/mgmt/recoveryservicesdatareplication/aio/operations/__init__.py
azure/mgmt/recoveryservicesdatareplication/aio/operations/_operations.py
azure/mgmt/recoveryservicesdatareplication/aio/operations/_patch.py
azure/mgmt/recoveryservicesdatareplication/models/__init__.py
azure/mgmt/recoveryservicesdatareplication/models/_enums.py
azure/mgmt/recoveryservicesdatareplication/models/_models.py
azure/mgmt/recoveryservicesdatareplication/models/_patch.py
azure/mgmt/recoveryservicesdatareplication/operations/__init__.py
azure/mgmt/recoveryservicesdatareplication/operations/_operations.py
azure/mgmt/recoveryservicesdatareplication/operations/_patch.py
azure_mgmt_recoveryservicesdatareplication-1.0.0.dist-info/LICENSE
azure_mgmt_recoveryservicesdatareplication-1.0.0.dist-info/METADATA
azure_mgmt_recoveryservicesdatareplication-1.0.0.dist-info/WHEEL
azure_mgmt_recoveryservicesdatareplication-1.0.0.dist-info/top_level.txt
azure_mgmt_recoveryservicesdatareplication-1.0.0.dist-info/RECORD
