Metadata-Version: 2.1
Name: azure-mgmt-recoveryservicesdatareplication
Version: 1.0.0
Summary: Microsoft Azure Recoveryservicesdatareplication Management Client Library for Python
Home-page: https://github.com/Azure/azure-sdk-for-python
Author: Microsoft Corporation
Author-email: azpysdkhelp@microsoft.com
License: MIT License
Keywords: azure,azure sdk
Classifier: Development Status :: 5 - Production/Stable
Classifier: Programming Language :: Python
Classifier: Programming Language :: Python :: 3 :: Only
Classifier: Programming Language :: Python :: 3
Classifier: Programming Language :: Python :: 3.9
Classifier: Programming Language :: Python :: 3.10
Classifier: Programming Language :: Python :: 3.11
Classifier: Programming Language :: Python :: 3.12
Classifier: License :: OSI Approved :: MIT License
Requires-Python: >=3.9
License-File: LICENSE
Requires-Dist: isodate>=0.6.1
Requires-Dist: typing-extensions>=4.6.0
Requires-Dist: azure-common>=1.1
Requires-Dist: azure-mgmt-core>=1.5.0
